pxr/Ar/__init__.py
pxr/Ar/__init__.pyi
pxr/Ar/_ar.so
pxr/Gf/__init__.py
pxr/Gf/__init__.pyi
pxr/Gf/_gf.so
pxr/Kind/__init__.py
pxr/Kind/__init__.pyi
pxr/Kind/_kind.so
pxr/Ndr/__init__.py
pxr/Ndr/__init__.pyi
pxr/Ndr/_ndr.so
pxr/Pcp/__init__.py
pxr/Pcp/__init__.pyi
pxr/Pcp/_pcp.so
pxr/Plug/__init__.py
pxr/Plug/__init__.pyi
pxr/Plug/_plug.so
pxr/Sdf/__init__.py
pxr/Sdf/__init__.pyi
pxr/Sdf/_sdf.so
pxr/Sdr/__init__.py
pxr/Sdr/__init__.pyi
pxr/Sdr/_sdr.so
pxr/Sdr/shaderParserTestUtils.py
pxr/Tf/__init__.py
pxr/Tf/_tf.pyi
pxr/Tf/_tf.so
pxr/Trace/__init__.py
pxr/Trace/__init__.pyi
pxr/Trace/__main__.py
pxr/Trace/_trace.so
pxr/Ts/TsTest_Baseliner.py
pxr/Ts/TsTest_Comparator.py
pxr/Ts/TsTest_Grapher.py
pxr/Ts/__init__.py
pxr/Ts/__init__.pyi
pxr/Ts/_ts.so
pxr/Usd/__init__.py
pxr/Usd/__init__.pyi
pxr/Usd/_usd.so
pxr/Usd/usdGenSchema.py
pxr/UsdGeom/__init__.py
pxr/UsdGeom/__init__.pyi
pxr/UsdGeom/_usdGeom.so
pxr/UsdLux/__init__.py
pxr/UsdLux/__init__.pyi
pxr/UsdLux/_usdLux.so
pxr/UsdPhysics/__init__.py
pxr/UsdPhysics/__init__.pyi
pxr/UsdPhysics/_usdPhysics.so
pxr/UsdSemantics/__init__.py
pxr/UsdSemantics/__init__.pyi
pxr/UsdSemantics/_usdSemantics.so
pxr/UsdShade/__init__.py
pxr/UsdShade/__init__.pyi
pxr/UsdShade/_usdShade.so
pxr/UsdSkel/__init__.py
pxr/UsdSkel/__init__.pyi
pxr/UsdSkel/_usdSkel.so
pxr/UsdUI/__init__.py
pxr/UsdUI/__init__.pyi
pxr/UsdUI/_usdUI.so
pxr/UsdUtils/__init__.py
pxr/UsdUtils/__init__.pyi
pxr/UsdUtils/_usdUtils.so
pxr/UsdUtils/complianceChecker.py
pxr/UsdUtils/constantsGroup.py
pxr/UsdUtils/fixBrokenPixarSchemas.py
pxr/UsdUtils/toolPaths.py
pxr/UsdUtils/updateSchemaWithSdrNode.py
pxr/UsdUtils/usdzUtils.py
pxr/Vt/__init__.py
pxr/Vt/__init__.pyi
pxr/Vt/_vt.so
pxr/Work/__init__.py
pxr/Work/__init__.pyi
pxr/Work/_work.so
usd_exchange.libs/libtbb-45454952.so.2
usd_exchange.libs/libusd_ar-f98cb08e.so
usd_exchange.libs/libusd_arch-c771d2ee.so
usd_exchange-2.2.0.dist-info/METADATA
usd_exchange-2.2.0.dist-info/WHEEL
usd_exchange-2.2.0.dist-info/RECORD
usd_exchange-2.2.0.dist-info/licenses/pybind11-LICENSE.txt
usd_exchange-2.2.0.dist-info/licenses/pyboost11-LICENSE.txt
usd_exchange-2.2.0.dist-info/licenses/tbb-LICENSE
usd_exchange-2.2.0.dist-info/licenses/usd-exchange-LICENSE.md
usd_exchange-2.2.0.dist-info/licenses/usd-license.txt
usd_exchange-2.2.0.dist-info/licenses/zlib-LICENSE.txt
