Metadata-Version: 2.4
Name: usd-exchange
Version: 2.2.0
Summary: OpenUSD Exchange provides higher-level convenience functions as a companion to lower-level OpenUSD concepts
License-Expression: Apache-2.0
License-File: pybind11-LICENSE.txt
License-File: pyboost11-LICENSE.txt
License-File: tbb-LICENSE
License-File: usd-exchange-LICENSE.md
License-File: usd-license.txt
License-File: zlib-LICENSE.txt
Author: NVIDIA
Requires-Python: >=3.10,<3.13
Classifier: Programming Language :: Python :: 3
Classifier: Programming Language :: Python :: 3.10
Classifier: Programming Language :: Python :: 3.11
Classifier: Programming Language :: Python :: 3.12
Provides-Extra: test
Provides-Extra: usd2505
Requires-Dist: omniverse-asset-validator (==1.9.2) ; extra == "test"
Project-URL: Changelog, https://docs.omniverse.nvidia.com/usd/code-docs/usd-exchange-sdk/latest/docs/changes.html
Project-URL: Documentation, https://docs.omniverse.nvidia.com/usd/code-docs/usd-exchange-sdk
Project-URL: Homepage, https://docs.omniverse.nvidia.com/usd/code-docs/usd-exchange-sdk
Project-URL: Repository, https://github.com/NVIDIA-Omniverse/usd-exchange
